withwait/__init__.py
withwait/__withwait.py
withwait/py.typed
withwait-0.1.2.dist-info/LICENSE.md
withwait-0.1.2.dist-info/METADATA
withwait-0.1.2.dist-info/WHEEL
withwait-0.1.2.dist-info/RECORD
