Metadata-Version: 2.1
Name: withwait
Version: 0.1.2
Summary: A simple utility to ensure that sleep operations always complete
Home-page: https://github.com/MaddyGuthridge/withwait
License: MIT
Keywords: testing,with,sleep,time,wait,delay
Author: Maddy Guthridge
Author-email: hello@maddyguthridge.com
Requires-Python: >=3.9,<4.0
Classifier: Development Status :: 4 - Beta
Classifier: Environment :: Other Environment
Classifier: Framework :: Pytest
Classifier: Intended Audience :: Developers
Classifier: License :: OSI Approved :: MIT License
Classifier: Operating System :: OS Independent
Classifier: Programming Language :: Python :: 3
Classifier: Programming Language :: Python :: 3.9
Classifier: Programming Language :: Python :: 3.10
Classifier: Programming Language :: Python :: 3.11
Classifier: Programming Language :: Python :: 3.12
Classifier: Topic :: Software Development :: Testing
Classifier: Typing :: Typed
Requires-Dist: typing-extensions (>=4.5.0,<5.0.0)
Project-URL: Bug Tracker, https://github.com/MaddyGuthridge/withwait/issues
Project-URL: Documentation, https://maddyguthridge.github.io/withwait
Project-URL: Online Documentation, https://github.com/MaddyGuthridge/withwait
Project-URL: Repository, https://github.com/MaddyGuthridge/withwait
